Classfile /C:/Users/Ryan/Google Drive/Bangor/_Y03/ICP 3099/jvm_prototype/build/classes/main/com/rfrench/jvm/simulatated_programs/WhileTest.class
  Last modified 21-Jan-2017; size 547 bytes
  MD5 checksum 9567ff6025a0813d48e6c163cd070a4f
  Compiled from "WhileTest.java"
public class main.com.rfrench.jvm.simulatated_programs.WhileTest
  minor version: 0
  major version: 52
  flags: ACC_PUBLIC, ACC_SUPER
Constant pool:
   #1 = Methodref          #3.#21         // java/lang/Object."<init>":()V
   #2 = Class              #22            // main/com/rfrench/jvm/simulatated_programs/WhileTest
   #3 = Class              #23            // java/lang/Object
   #4 = Utf8               <init>
   #5 = Utf8               ()V
   #6 = Utf8               Code
   #7 = Utf8               LineNumberTable
   #8 = Utf8               LocalVariableTable
   #9 = Utf8               this
  #10 = Utf8               Lmain/com/rfrench/jvm/simulatated_programs/WhileTest;
  #11 = Utf8               main
  #12 = Utf8               ([Ljava/lang/String;)V
  #13 = Utf8               args
  #14 = Utf8               [Ljava/lang/String;
  #15 = Utf8               a
  #16 = Utf8               I
  #17 = Utf8               b
  #18 = Utf8               StackMapTable
  #19 = Utf8               SourceFile
  #20 = Utf8               WhileTest.java
  #21 = NameAndType        #4:#5          // "<init>":()V
  #22 = Utf8               main/com/rfrench/jvm/simulatated_programs/WhileTest
  #23 = Utf8               java/lang/Object
{
  public main.com.rfrench.jvm.simulatated_programs.WhileTest();
    descriptor: ()V
    flags: ACC_PUBLIC
    Code:
      stack=1, locals=1, args_size=1
         0: aload_0
         1: invokespecial #1                  // Method java/lang/Object."<init>":()V
         4: return
      LineNumberTable:
        line 12: 0
      LocalVariableTable:
        Start  Length  Slot  Name   Signature
            0       5     0  this   Lmain/com/rfrench/jvm/simulatated_programs/WhileTest;

  public static void main(java.lang.String[]);
    descriptor: ([Ljava/lang/String;)V
    flags: ACC_PUBLIC, ACC_STATIC
    Code:
      stack=2, locals=3, args_size=1
         0: iconst_5
         1: istore_1
         2: iconst_0
         3: istore_2
         4: iload_2
         5: iload_1
         6: if_icmpge     15
         9: iinc          2, 1
        12: goto          4
        15: return
      LineNumberTable:
        line 16: 0
        line 17: 2
        line 19: 4
        line 21: 9
        line 24: 15
      LocalVariableTable:
        Start  Length  Slot  Name   Signature
            0      16     0  args   [Ljava/lang/String;
            2      14     1     a   I
            4      12     2     b   I
      StackMapTable: number_of_entries = 2
        frame_type = 253 /* append */
          offset_delta = 4
          locals = [ int, int ]
        frame_type = 10 /* same */
}
SourceFile: "WhileTest.java"
