

Classfile /C:/Users/Ryan/Google Drive/Bangor/_Y03/ICP 3099/jvm_prototype/build/classes/main/com/rfrench/jvm/simulatated_programs/TestObject.class
  Last modified 22-Jan-2017; size 411 bytes
  MD5 checksum 72cf88a9ccac311637121d1d2ab4d2cb
  Compiled from "TestObject.java"
public class main.com.rfrench.jvm.simulatated_programs.TestObject
  minor version: 0
  major version: 52
  flags: ACC_PUBLIC, ACC_SUPER
Constant pool:
   #1 = Methodref          #5.#18         // java/lang/Object."<init>":()V
   #2 = Fieldref           #4.#19         // main/com/rfrench/jvm/simulatated_programs/TestObject.a:I
   #3 = Fieldref           #4.#20         // main/com/rfrench/jvm/simulatated_programs/TestObject.b:I
   #4 = Class              #21            // main/com/rfrench/jvm/simulatated_programs/TestObject
   #5 = Class              #22            // java/lang/Object
   #6 = Utf8               a
   #7 = Utf8               I
   #8 = Utf8               b
   #9 = Utf8               <init>
  #10 = Utf8               ()V
  #11 = Utf8               Code
  #12 = Utf8               LineNumberTable
  #13 = Utf8               LocalVariableTable
  #14 = Utf8               this
  #15 = Utf8               Lmain/com/rfrench/jvm/simulatated_programs/TestObject;
  #16 = Utf8               SourceFile
  #17 = Utf8               TestObject.java
  #18 = NameAndType        #9:#10         // "<init>":()V
  #19 = NameAndType        #6:#7          // a:I
  #20 = NameAndType        #8:#7          // b:I
  #21 = Utf8               main/com/rfrench/jvm/simulatated_programs/TestObject
  #22 = Utf8               java/lang/Object
{
  private int a;
    descriptor: I
    flags: ACC_PRIVATE

  private int b;
    descriptor: I
    flags: ACC_PRIVATE

  public main.com.rfrench.jvm.simulatated_programs.TestObject();
    descriptor: ()V
    flags: ACC_PUBLIC
    Code:
      stack=2, locals=1, args_size=1
         0: aload_0
         1: invokespecial #1                  // Method java/lang/Object."<init>":()V
         4: aload_0
         5: bipush        10
         7: putfield      #2                  // Field a:I
        10: aload_0
        11: bipush        -12
        13: putfield      #3                  // Field b:I
        16: return
      LineNumberTable:
        line 19: 0
        line 20: 4
        line 22: 10
        line 23: 16
      LocalVariableTable:
        Start  Length  Slot  Name   Signature
            0      17     0  this   Lmain/com/rfrench/jvm/simulatated_programs/TestObject;
}
SourceFile: "TestObject.java"
